Workbook

Sheet Cronograma
A1: EcosistemaIA — Plan de Trabajo (Piloto Ventas hasta 15/02/2027 + RBAC ampliado)
A3: ID | B3: Fase | C3: Tarea | D3: Responsable | E3: Área | F3: Inicio | G3: Fin | H3: Duración (días) | I3: Estado | J3: % Avance
A4: 1 | B4: Fase 0 | C4: Aprobación de alcance (Fase 0) | D4: Manuel / Oscar | E4: Ejecutiva | F4: 46258 | G4: 46262 | H4: =G4-F4+1 | I4: Pendiente | J4: 0
A5: 2 | B5: Fase 0 | C5: Aprobación de presupuesto CAPEX | D5: Finanzas / Manuel | E5: Ejecutiva | F5: 46258 | G5: 46262 | H5: =G5-F5+1 | I5: Pendiente | J5: 0
A6: 3 | B6: Fase 0 | C6: Definir responsable técnico (Héctor / recurso) | D6: Manuel | E6: TI | F6: 46258 | G6: 46262 | H6: =G6-F6+1 | I6: Pendiente | J6: 0
A7: 4 | B7: Fase 0 | C7: Acceso a APIs SAP C4C y SAP FSM | D7: TI | E7: TI | F7: 46265 | G7: 46276 | H7: =G7-F7+1 | I7: Pendiente | J7: 0
A8: 5 | B8: Fase 0 | C8: Catálogo de preguntas del piloto - Ventas | D8: Oscar / Ventas | E8: Ventas | F8: 46265 | G8: 46269 | H8: =G8-F8+1 | I8: Completado | J8: 1
A9: 6 | B9: Fase 0 | C9: Diseño de capa de permisos (RBAC piloto) | D9: TI | E9: TI | F9: 46265 | G9: 46276 | H9: =G9-F9+1 | I9: Completado | J9: 1
A10: 7 | B10: Fase 0 | C10: Desarrollo del orquestador (prototipo) | D10: Oscar | E10: TI | F10: 46279 | G10: 46297 | H10: =G10-F10+1 | I10: Completado | J10: 1
A11: 8 | B11: Fase 0 | C11: Integración con SQL central | D11: Oscar | E11: TI | F11: 46279 | G11: 46290 | H11: =G11-F11+1 | I11: Completado | J11: 1
A12: 9 | B12: Fase 0 | C12: Testing y ajuste de prompts | D12: Oscar | E12: TI | F12: 46300 | G12: 46311 | H12: =G12-F12+1 | I12: Completado | J12: 1
A13: 10 | B13: Fase 0 | C13: Medición de consumo real de tokens | D13: TI | E13: TI | F13: 46307 | G13: 46311 | H13: =G13-F13+1 | I13: Pendiente | J13: 0
A14: 11 | B14: Fase 0 | C14: Ajuste de OPEX con datos reales | D14: Oscar | E14: Oscar | F14: 46314 | G14: 46318 | H14: =G14-F14+1 | I14: Pendiente | J14: 0
A15: 12 | B15: Fase 0 | C15: Piloto en producción - Ventas | D15: Ventas / TI | E15: Ventas | F15: 46314 | G15: 46433 | H15: =G15-F15+1 | I15: Pendiente | J15: 0
A16: 13 | B16: Fase 0 | C16: Evaluación de resultados piloto Ventas | D16: Oscar / Manuel | E16: Oscar | F16: 46440 | G16: 46444 | H16: =G16-F16+1 | I16: Pendiente | J16: 0
A17: 5b | B17: Fase 0 | C17: 7 herramientas analíticas Fase 0+ (gap, inactivos, canal, tendencia, nuevos clientes, margen, reporte) | D17: Oscar | E17: TI | F17: 46252 | G17: 46253 | H17: =G17-F17+1 | I17: Completado | J17: 1
A18: 5c | B18: Fase 0 | C18: Fix: mes incompleto excluido en tendencia y forecast; RBAC verificado; test con roles reales | D18: Oscar | E18: TI | F18: 46253 | G18: 46253 | H18: =G18-F18+1 | I18: Completado | J18: 1
A19: 5d | B19: Fase 0 | C19: Deploy Azure Container Apps (pendiente credenciales del coordinador funcional) | D19: Oscar / TI | E19: TI | F19: 46253 | G19: 46270 | H19: =G19-F19+1 | I19: En Progreso | J19: 0.2
A20: 14 | B20: Fase 1 | C20: Ampliación - UN Institucional: Catálogo | D20: Oscar / UN Inst. | E20: UN Inst. | F20: 46447 | G20: 46451 | H20: =G17-F17+1 | I20: Pendiente | J20: 0
A21: 15 | B21: Fase 1 | C21: Ampliación - UN Institucional: Testing | D21: Oscar | E21: TI | F21: 46454 | G21: 46465 | H21: =G18-F18+1 | I21: Pendiente | J21: 0
A22: 16 | B22: Fase 1 | C22: Ampliación - UN Institucional: Deploy | D22: UN Inst. / TI | E22: UN Inst. | F22: 46468 | G22: 46479 | H22: =G19-F19+1 | I22: Pendiente | J22: 0
A23: 17 | B23: Fase 1 | C23: Ampliación - Metusa: Catálogo | D23: Oscar / Metusa | E23: Metusa | F23: 46447 | G23: 46451 | H23: =G20-F20+1 | I23: Pendiente | J23: 0
A24: 18 | B24: Fase 1 | C24: Ampliación - Metusa: Testing | D24: Oscar | E24: TI | F24: 46454 | G24: 46465 | H24: =G21-F21+1 | I24: Pendiente | J24: 0
A25: 19 | B25: Fase 1 | C25: Ampliación - Metusa: Deploy | D25: Metusa / TI | E25: Metusa | F25: 46468 | G25: 46479 | H25: =G22-F22+1 | I25: Pendiente | J25: 0
A26: 20 | B26: Fase 1 | C26: Ampliación - Atención al Cliente: Catálogo | D26: Oscar / Atención | E26: Atención al Cliente | F26: 46447 | G26: 46451 | H26: =G23-F23+1 | I26: Pendiente | J26: 0
A27: 21 | B27: Fase 1 | C27: Ampliación - Atención al Cliente: Testing | D27: Oscar | E27: TI | F27: 46454 | G27: 46465 | H27: =G24-F24+1 | I27: Pendiente | J27: 0
A28: 22 | B28: Fase 1 | C28: Ampliación - Atención al Cliente: Deploy | D28: Atención / TI | E28: Atención al Cliente | F28: 46468 | G28: 46479 | H28: =G25-F25+1 | I28: Pendiente | J28: 0
A29: 23 | B29: Fase 1 | C29: Ampliación - Innovación/Calidad: Catálogo | D29: Oscar / Innovación | E29: Innovación y Calidad | F29: 46447 | G29: 46451 | H29: =G26-F26+1 | I29: Pendiente | J29: 0
A30: 24 | B30: Fase 1 | C30: Ampliación - Innovación/Calidad: Testing | D30: Oscar | E30: TI | F30: 46454 | G30: 46465 | H30: =G27-F27+1 | I30: Pendiente | J30: 0
A31: 25 | B31: Fase 1 | C31: Ampliación - Innovación/Calidad: Deploy | D31: Innovación / TI | E31: Innovación y Calidad | F31: 46468 | G31: 46479 | H31: =G28-F28+1 | I31: Pendiente | J31: 0
... A58: 52 | B58: Fase 3 | C58: Rollout general completado | D58: Ejecutiva | E58: Ejecutiva | F58: 46734 | G58: 46752 | H58: =G55-F55+1 | I58: Pendiente | J58: 0

Sheet Supuestos
A1: SUPUESTOS DEL PROYECTO
A3: 1. EQUIPO Y RECURSOS
A5: Oscar Armando Núñez Vargas | B5: Especialista de Transformación Digital e IA | C5: Desarrollo con Claude, coordinación, gestión stakeholders
A6: Héctor Antaurco Ayca | B6: Analista de Procesos y Data | C6: Validación de datos, catalogación de preguntas, documentación
A7: Manuel Calderón Montoro | B7: Jefe de TI | C7: Aprobación, acceso a infraestructura, supervisión
A8: Andrea Cárdenas Silva | B8: Jefe de RRHH/Procesos | C8: Validación de RRHH, documentación institucional
A9: Renato Saldaña Jaimes | B9: Jefe Legal | C9: Validación legal, cumplimiento de datos personales
A11: 2. SUPUESTOS DE DISPONIBILIDAD
A13: Oscar dedicación | B13: ~70% (estimado) | C13: Desarrollo con Claude + coordinación + reuniones stakeholders
A14: Héctor dedicación | B14: ~20% (estimado) | C14: Validación en paralelo, no es bloqueante del desarrollo
A15: Acceso SAP C4C/FSM | B15: 31 ago 2026 | C15: Requerido para inicio del desarrollo del orquestador
A16: Disponibilidad SQL central | B16: 31 ago 2026 | C16: Datos centrales ya existen, integración en plataforma
A18: 3. SUPUESTOS DE TECNOLOGÍA
A20: Claude como herramienta de desarrollo | B20: Acelera desarrollo ~3-5x vs. programador manual | C20: Pruebas iniciales exitosas con intake platform
A21: Modelo LLM | B21: Claude Sonnet 5 o superior | C21: Function calling maduro, 200K token window
A22: Arquitectura | B22: A definir (Orquestador único vs. Multiagente) | C22: Análisis de tokens dice ~24% ahorro con multiagente
A23: Hosting | B23: Azure / infraestructura MT Industrial existente | C23: TI responsable de infraestructura
A25: 4. RIESGOS PRINCIPALES
A27: Oscar indisponible | B27: ALTO | C27: Mitigación: documentar código, establecer backup
A28: RBAC más complejo de lo estimado | B28: MEDIO | C28: Incluir buffer en cronograma, validar con Legal desde inicio
A29: Alucinaciones LLM en datos sensibles (RRHH/Legal) | B29: ALTO | C29: Guardrails + validación humana en Fase 2
A30: Acceso tardío a APIs SAP | B30: MEDIO | C30: Inicio paralelo: desarrollo sin SAP usando datos de prueba
A31: Presunción en proyecciones (climate, market) | B31: MEDIO | C31: Documentar variables externas, marcar como supuestos en UI

Sheet Gantt
A1: EcosistemaIA — Gantt por Mes (todas las áreas y fases)
A3: ID | B3: Fase | C3: Tarea | D3: Área | E3: Aug 2026 | F3: Sep 2026 | G3: Oct 2026 | H3: Nov 2026 | I3: Dec 2026 | J3: Jan 2027 | K3: Feb 2027 | L3: Mar 2027 | M3: Apr 2027 | N3: May 2027 | O3: Jun 2027 | P3: Jul 2027 | Q3: Aug 2027 | R3: Sep 2027 | S3: Oct 2027 | T3: Nov 2027 | U3: Dec 2027
A4: =Cronograma!A5 | B4: =Cronograma!B5 | C4: =Cronograma!C5 | D4: =Cronograma!E5 | E4: =IF(AND(Cronograma!$F5<=DATE(2026,8,31),Cronograma!$G5>=DATE(2026,8,1)),1,0) | F4: =IF(AND(Cronograma!$F5<=DATE(2026,9,30),Cronograma!$G5>=DATE(2026,9,1)),1,0) | G4: =IF(AND(Cronograma!$F5<=DATE(2026,10,31),Cronograma!$G5>=DATE(2026,10,1)),1,0) | H4: =IF(AND(Cronograma!$F5<=DATE(2026,11,30),Cronograma!$G5>=DATE(2026,11,1)),1,0) | I4: =IF(AND(Cronograma!$F5<=DATE(2026,12,31),Cronograma!$G5>=DATE(2026,12,1)),1,0) | J4: =IF(AND(Cronograma!$F5<=DATE(2027,1,31),Cronograma!$G5>=DATE(2027,1,1)),1,0) | K4: =IF(AND(Cronograma!$F5<=DATE(2027,2,28),Cronograma!$G5>=DATE(2027,2,1)),1,0) | L4: =IF(AND(Cronograma!$F5<=DATE(2027,3,31),Cronograma!$G5>=DATE(2027,3,1)),1,0) | M4: =IF(AND(Cronograma!$F5<=DATE(2027,4,30),Cronograma!$G5>=DATE(2027,4,1)),1,0) | N4: =IF(AND(Cronograma!$F5<=DATE(2027,5,31),Cronograma!$G5>=DATE(2027,5,1)),1,0) | O4: =IF(AND(Cronograma!$F5<=DATE(2027,6,30),Cronograma!$G5>=DATE(2027,6,1)),1,0) | P4: =IF(AND(Cronograma!$F5<=DATE(2027,7,31),Cronograma!$G5>=DATE(2027,7,1)),1,0) | Q4: =IF(AND(Cronograma!$F5<=DATE(2027,8,31),Cronograma!$G5>=DATE(2027,8,1)),1,0) | R4: =IF(AND(Cronograma!$F5<=DATE(2027,9,30),Cronograma!$G5>=DATE(2027,9,1)),1,0) | S4: =IF(AND(Cronograma!$F5<=DATE(2027,10,31),Cronograma!$G5>=DATE(2027,10,1)),1,0) | T4: =IF(AND(Cronograma!$F5<=DATE(2027,11,30),Cronograma!$G5>=DATE(2027,11,1)),1,0) | U4: =IF(AND(Cronograma!$F5<=DATE(2027,12,31),Cronograma!$G5>=DATE(2027,12,1)),1,0)
A5: =Cronograma!A6 | B5: =Cronograma!B6 | C5: =Cronograma!C6 | D5: =Cronograma!E6 | E5: =IF(AND(Cronograma!$F6<=DATE(2026,8,31),Cronograma!$G6>=DATE(2026,8,1)),1,0) | F5: =IF(AND(Cronograma!$F6<=DATE(2026,9,30),Cronograma!$G6>=DATE(2026,9,1)),1,0) | G5: =IF(AND(Cronograma!$F6<=DATE(2026,10,31),Cronograma!$G6>=DATE(2026,10,1)),1,0) | H5: =IF(AND(Cronograma!$F6<=DATE(2026,11,30),Cronograma!$G6>=DATE(2026,11,1)),1,0) | I5: =IF(AND(Cronograma!$F6<=DATE(2026,12,31),Cronograma!$G6>=DATE(2026,12,1)),1,0) | J5: =IF(AND(Cronograma!$F6<=DATE(2027,1,31),Cronograma!$G6>=DATE(2027,1,1)),1,0) | K5: =IF(AND(Cronograma!$F6<=DATE(2027,2,28),Cronograma!$G6>=DATE(2027,2,1)),1,0) | L5: =IF(AND(Cronograma!$F6<=DATE(2027,3,31),Cronograma!$G6>=DATE(2027,3,1)),1,0) | M5: =IF(AND(Cronograma!$F6<=DATE(2027,4,30),Cronograma!$G6>=DATE(2027,4,1)),1,0) | N5: =IF(AND(Cronograma!$F6<=DATE(2027,5,31),Cronograma!$G6>=DATE(2027,5,1)),1,0) | O5: =IF(AND(Cronograma!$F6<=DATE(2027,6,30),Cronograma!$G6>=DATE(2027,6,1)),1,0) | P5: =IF(AND(Cronograma!$F6<=DATE(2027,7,31),Cronograma!$G6>=DATE(2027,7,1)),1,0) | Q5: =IF(AND(Cronograma!$F6<=DATE(2027,8,31),Cronograma!$G6>=DATE(2027,8,1)),1,0) | R5: =IF(AND(Cronograma!$F6<=DATE(2027,9,30),Cronograma!$G6>=DATE(2027,9,1)),1,0) | S5: =IF(AND(Cronograma!$F6<=DATE(2027,10,31),Cronograma!$G6>=DATE(2027,10,1)),1,0) | T5: =IF(AND(Cronograma!$F6<=DATE(2027,11,30),Cronograma!$G6>=DATE(2027,11,1)),1,0) | U5: =IF(AND(Cronograma!$F6<=DATE(2027,12,31),Cronograma!$G6>=DATE(2027,12,1)),1,0)
A6: =Cronograma!A7 | B6: =Cronograma!B7 | C6: =Cronograma!C7 | D6: =Cronograma!E7 | E6: =IF(AND(Cronograma!$F7<=DATE(2026,8,31),Cronograma!$G7>=DATE(2026,8,1)),1,0) | F6: =IF(AND(Cronograma!$F7<=DATE(2026,9,30),Cronograma!$G7>=DATE(2026,9,1)),1,0) | G6: =IF(AND(Cronograma!$F7<=DATE(2026,10,31),Cronograma!$G7>=DATE(2026,10,1)),1,0) | H6: =IF(AND(Cronograma!$F7<=DATE(2026,11,30),Cronograma!$G7>=DATE(2026,11,1)),1,0) | I6: =IF(AND(Cronograma!$F7<=DATE(2026,12,31),Cronograma!$G7>=DATE(2026,12,1)),1,0) | J6: =IF(AND(Cronograma!$F7<=DATE(2027,1,31),Cronograma!$G7>=DATE(2027,1,1)),1,0) | K6: =IF(AND(Cronograma!$F7<=DATE(2027,2,28),Cronograma!$G7>=DATE(2027,2,1)),1,0) | L6: =IF(AND(Cronograma!$F7<=DATE(2027,3,31),Cronograma!$G7>=DATE(2027,3,1)),1,0) | M6: =IF(AND(Cronograma!$F7<=DATE(2027,4,30),Cronograma!$G7>=DATE(2027,4,1)),1,0) | N6: =IF(AND(Cronograma!$F7<=DATE(2027,5,31),Cronograma!$G7>=DATE(2027,5,1)),1,0) | O6: =IF(AND(Cronograma!$F7<=DATE(2027,6,30),Cronograma!$G7>=DATE(2027,6,1)),1,0) | P6: =IF(AND(Cronograma!$F7<=DATE(2027,7,31),Cronograma!$G7>=DATE(2027,7,1)),1,0) | Q6: =IF(AND(Cronograma!$F7<=DATE(2027,8,31),Cronograma!$G7>=DATE(2027,8,1)),1,0) | R6: =IF(AND(Cronograma!$F7<=DATE(2027,9,30),Cronograma!$G7>=DATE(2027,9,1)),1,0) | S6: =IF(AND(Cronograma!$F7<=DATE(2027,10,31),Cronograma!$G7>=DATE(2027,10,1)),1,0) | T6: =IF(AND(Cronograma!$F7<=DATE(2027,11,30),Cronograma!$G7>=DATE(2027,11,1)),1,0) | U6: =IF(AND(Cronograma!$F7<=DATE(2027,12,31),Cronograma!$G7>=DATE(2027,12,1)),1,0)
A7: =Cronograma!A8 | B7: =Cronograma!B8 | C7: =Cronograma!C8 | D7: =Cronograma!E8 | E7: =IF(AND(Cronograma!$F8<=DATE(2026,8,31),Cronograma!$G8>=DATE(2026,8,1)),1,0) | F7: =IF(AND(Cronograma!$F8<=DATE(2026,9,30),Cronograma!$G8>=DATE(2026,9,1)),1,0) | G7: =IF(AND(Cronograma!$F8<=DATE(2026,10,31),Cronograma!$G8>=DATE(2026,10,1)),1,0) | H7: =IF(AND(Cronograma!$F8<=DATE(2026,11,30),Cronograma!$G8>=DATE(2026,11,1)),1,0) | I7: =IF(AND(Cronograma!$F8<=DATE(2026,12,31),Cronograma!$G8>=DATE(2026,12,1)),1,0) | J7: =IF(AND(Cronograma!$F8<=DATE(2027,1,31),Cronograma!$G8>=DATE(2027,1,1)),1,0) | K7: =IF(AND(Cronograma!$F8<=DATE(2027,2,28),Cronograma!$G8>=DATE(2027,2,1)),1,0) | L7: =IF(AND(Cronograma!$F8<=DATE(2027,3,31),Cronograma!$G8>=DATE(2027,3,1)),1,0) | M7: =IF(AND(Cronograma!$F8<=DATE(2027,4,30),Cronograma!$G8>=DATE(2027,4,1)),1,0) | N7: =IF(AND(Cronograma!$F8<=DATE(2027,5,31),Cronograma!$G8>=DATE(2027,5,1)),1,0) | O7: =IF(AND(Cronograma!$F8<=DATE(2027,6,30),Cronograma!$G8>=DATE(2027,6,1)),1,0) | P7: =IF(AND(Cronograma!$F8<=DATE(2027,7,31),Cronograma!$G8>=DATE(2027,7,1)),1,0) | Q7: =IF(AND(Cronograma!$F8<=DATE(2027,8,31),Cronograma!$G8>=DATE(2027,8,1)),1,0) | R7: =IF(AND(Cronograma!$F8<=DATE(2027,9,30),Cronograma!$G8>=DATE(2027,9,1)),1,0) | S7: =IF(AND(Cronograma!$F8<=DATE(2027,10,31),Cronograma!$G8>=DATE(2027,10,1)),1,0) | T7: =IF(AND(Cronograma!$F8<=DATE(2027,11,30),Cronograma!$G8>=DATE(2027,11,1)),1,0) | U7: =IF(AND(Cronograma!$F8<=DATE(2027,12,31),Cronograma!$G8>=DATE(2027,12,1)),1,0)
A8: =Cronograma!A9 | B8: =Cronograma!B9 | C8: =Cronograma!C9 | D8: =Cronograma!E9 | E8: =IF(AND(Cronograma!$F9<=DATE(2026,8,31),Cronograma!$G9>=DATE(2026,8,1)),1,0) | F8: =IF(AND(Cronograma!$F9<=DATE(2026,9,30),Cronograma!$G9>=DATE(2026,9,1)),1,0) | G8: =IF(AND(Cronograma!$F9<=DATE(2026,10,31),Cronograma!$G9>=DATE(2026,10,1)),1,0) | H8: =IF(AND(Cronograma!$F9<=DATE(2026,11,30),Cronograma!$G9>=DATE(2026,11,1)),1,0) | I8: =IF(AND(Cronograma!$F9<=DATE(2026,12,31),Cronograma!$G9>=DATE(2026,12,1)),1,0) | J8: =IF(AND(Cronograma!$F9<=DATE(2027,1,31),Cronograma!$G9>=DATE(2027,1,1)),1,0) | K8: =IF(AND(Cronograma!$F9<=DATE(2027,2,28),Cronograma!$G9>=DATE(2027,2,1)),1,0) | L8: =IF(AND(Cronograma!$F9<=DATE(2027,3,31),Cronograma!$G9>=DATE(2027,3,1)),1,0) | M8: =IF(AND(Cronograma!$F9<=DATE(2027,4,30),Cronograma!$G9>=DATE(2027,4,1)),1,0) | N8: =IF(AND(Cronograma!$F9<=DATE(2027,5,31),Cronograma!$G9>=DATE(2027,5,1)),1,0) | O8: =IF(AND(Cronograma!$F9<=DATE(2027,6,30),Cronograma!$G9>=DATE(2027,6,1)),1,0) | P8: =IF(AND(Cronograma!$F9<=DATE(2027,7,31),Cronograma!$G9>=DATE(2027,7,1)),1,0) | Q8: =IF(AND(Cronograma!$F9<=DATE(2027,8,31),Cronograma!$G9>=DATE(2027,8,1)),1,0) | R8: =IF(AND(Cronograma!$F9<=DATE(2027,9,30),Cronograma!$G9>=DATE(2027,9,1)),1,0) | S8: =IF(AND(Cronograma!$F9<=DATE(2027,10,31),Cronograma!$G9>=DATE(2027,10,1)),1,0) | T8: =IF(AND(Cronograma!$F9<=DATE(2027,11,30),Cronograma!$G9>=DATE(2027,11,1)),1,0) | U8: =IF(AND(Cronograma!$F9<=DATE(2027,12,31),Cronograma!$G9>=DATE(2027,12,1)),1,0)
A9: =Cronograma!A10 | B9: =Cronograma!B10 | C9: =Cronograma!C10 | D9: =Cronograma!E10 | E9: =IF(AND(Cronograma!$F10<=DATE(2026,8,31),Cronograma!$G10>=DATE(2026,8,1)),1,0) | F9: =IF(AND(Cronograma!$F10<=DATE(2026,9,30),Cronograma!$G10>=DATE(2026,9,1)),1,0) | G9: =IF(AND(Cronograma!$F10<=DATE(2026,10,31),Cronograma!$G10>=DATE(2026,10,1)),1,0) | H9: =IF(AND(Cronograma!$F10<=DATE(2026,11,30),Cronograma!$G10>=DATE(2026,11,1)),1,0) | I9: =IF(AND(Cronograma!$F10<=DATE(2026,12,31),Cronograma!$G10>=DATE(2026,12,1)),1,0) | J9: =IF(AND(Cronograma!$F10<=DATE(2027,1,31),Cronograma!$G10>=DATE(2027,1,1)),1,0) | K9: =IF(AND(Cronograma!$F10<=DATE(2027,2,28),Cronograma!$G10>=DATE(2027,2,1)),1,0) | L9: =IF(AND(Cronograma!$F10<=DATE(2027,3,31),Cronograma!$G10>=DATE(2027,3,1)),1,0) | M9: =IF(AND(Cronograma!$F10<=DATE(2027,4,30),Cronograma!$G10>=DATE(2027,4,1)),1,0) | N9: =IF(AND(Cronograma!$F10<=DATE(2027,5,31),Cronograma!$G10>=DATE(2027,5,1)),1,0) | O9: =IF(AND(Cronograma!$F10<=DATE(2027,6,30),Cronograma!$G10>=DATE(2027,6,1)),1,0) | P9: =IF(AND(Cronograma!$F10<=DATE(2027,7,31),Cronograma!$G10>=DATE(2027,7,1)),1,0) | Q9: =IF(AND(Cronograma!$F10<=DATE(2027,8,31),Cronograma!$G10>=DATE(2027,8,1)),1,0) | R9: =IF(AND(Cronograma!$F10<=DATE(2027,9,30),Cronograma!$G10>=DATE(2027,9,1)),1,0) | S9: =IF(AND(Cronograma!$F10<=DATE(2027,10,31),Cronograma!$G10>=DATE(2027,10,1)),1,0) | T9: =IF(AND(Cronograma!$F10<=DATE(2027,11,30),Cronograma!$G10>=DATE(2027,11,1)),1,0) | U9: =IF(AND(Cronograma!$F10<=DATE(2027,12,31),Cronograma!$G10>=DATE(2027,12,1)),1,0)
A10: =Cronograma!A11 | B10: =Cronograma!B11 | C10: =Cronograma!C11 | D10: =Cronograma!E11 | E10: =IF(AND(Cronograma!$F11<=DATE(2026,8,31),Cronograma!$G11>=DATE(2026,8,1)),1,0) | F10: =IF(AND(Cronograma!$F11<=DATE(2026,9,30),Cronograma!$G11>=DATE(2026,9,1)),1,0) | G10: =IF(AND(Cronograma!$F11<=DATE(2026,10,31),Cronograma!$G11>=DATE(2026,10,1)),1,0) | H10: =IF(AND(Cronograma!$F11<=DATE(2026,11,30),Cronograma!$G11>=DATE(2026,11,1)),1,0) | I10: =IF(AND(Cronograma!$F11<=DATE(2026,12,31),Cronograma!$G11>=DATE(2026,12,1)),1,0) | J10: =IF(AND(Cronograma!$F11<=DATE(2027,1,31),Cronograma!$G11>=DATE(2027,1,1)),1,0) | K10: =IF(AND(Cronograma!$F11<=DATE(2027,2,28),Cronograma!$G11>=DATE(2027,2,1)),1,0) | L10: =IF(AND(Cronograma!$F11<=DATE(2027,3,31),Cronograma!$G11>=DATE(2027,3,1)),1,0) | M10: =IF(AND(Cronograma!$F11<=DATE(2027,4,30),Cronograma!$G11>=DATE(2027,4,1)),1,0) | N10: =IF(AND(Cronograma!$F11<=DATE(2027,5,31),Cronograma!$G11>=DATE(2027,5,1)),1,0) | O10: =IF(AND(Cronograma!$F11<=DATE(2027,6,30),Cronograma!$G11>=DATE(2027,6,1)),1,0) | P10: =IF(AND(Cronograma!$F11<=DATE(2027,7,31),Cronograma!$G11>=DATE(2027,7,1)),1,0) | Q10: =IF(AND(Cronograma!$F11<=DATE(2027,8,31),Cronograma!$G11>=DATE(2027,8,1)),1,0) | R10: =IF(AND(Cronograma!$F11<=DATE(2027,9,30),Cronograma!$G11>=DATE(2027,9,1)),1,0) | S10: =IF(AND(Cronograma!$F11<=DATE(2027,10,31),Cronograma!$G11>=DATE(2027,10,1)),1,0) | T10: =IF(AND(Cronograma!$F11<=DATE(2027,11,30),Cronograma!$G11>=DATE(2027,11,1)),1,0) | U10: =IF(AND(Cronograma!$F11<=DATE(2027,12,31),Cronograma!$G11>=DATE(2027,12,1)),1,0)
A11: =Cronograma!A12 | B11: =Cronograma!B12 | C11: =Cronograma!C12 | D11: =Cronograma!E12 | E11: =IF(AND(Cronograma!$F12<=DATE(2026,8,31),Cronograma!$G12>=DATE(2026,8,1)),1,0) | F11: =IF(AND(Cronograma!$F12<=DATE(2026,9,30),Cronograma!$G12>=DATE(2026,9,1)),1,0) | G11: =IF(AND(Cronograma!$F12<=DATE(2026,10,31),Cronograma!$G12>=DATE(2026,10,1)),1,0) | H11: =IF(AND(Cronograma!$F12<=DATE(2026,11,30),Cronograma!$G12>=DATE(2026,11,1)),1,0) | I11: =IF(AND(Cronograma!$F12<=DATE(2026,12,31),Cronograma!$G12>=DATE(2026,12,1)),1,0) | J11: =IF(AND(Cronograma!$F12<=DATE(2027,1,31),Cronograma!$G12>=DATE(2027,1,1)),1,0) | K11: =IF(AND(Cronograma!$F12<=DATE(2027,2,28),Cronograma!$G12>=DATE(2027,2,1)),1,0) | L11: =IF(AND(Cronograma!$F12<=DATE(2027,3,31),Cronograma!$G12>=DATE(2027,3,1)),1,0) | M11: =IF(AND(Cronograma!$F12<=DATE(2027,4,30),Cronograma!$G12>=DATE(2027,4,1)),1,0) | N11: =IF(AND(Cronograma!$F12<=DATE(2027,5,31),Cronograma!$G12>=DATE(2027,5,1)),1,0) | O11: =IF(AND(Cronograma!$F12<=DATE(2027,6,30),Cronograma!$G12>=DATE(2027,6,1)),1,0) | P11: =IF(AND(Cronograma!$F12<=DATE(2027,7,31),Cronograma!$G12>=DATE(2027,7,1)),1,0) | Q11: =IF(AND(Cronograma!$F12<=DATE(2027,8,31),Cronograma!$G12>=DATE(2027,8,1)),1,0) | R11: =IF(AND(Cronograma!$F12<=DATE(2027,9,30),Cronograma!$G12>=DATE(2027,9,1)),1,0) | S11: =IF(AND(Cronograma!$F12<=DATE(2027,10,31),Cronograma!$G12>=DATE(2027,10,1)),1,0) | T11: =IF(AND(Cronograma!$F12<=DATE(2027,11,30),Cronograma!$G12>=DATE(2027,11,1)),1,0) | U11: =IF(AND(Cronograma!$F12<=DATE(2027,12,31),Cronograma!$G12>=DATE(2027,12,1)),1,0)
A12: =Cronograma!A13 | B12: =Cronograma!B13 | C12: =Cronograma!C13 | D12: =Cronograma!E13 | E12: =IF(AND(Cronograma!$F13<=DATE(2026,8,31),Cronograma!$G13>=DATE(2026,8,1)),1,0) | F12: =IF(AND(Cronograma!$F13<=DATE(2026,9,30),Cronograma!$G13>=DATE(2026,9,1)),1,0) | G12: =IF(AND(Cronograma!$F13<=DATE(2026,10,31),Cronograma!$G13>=DATE(2026,10,1)),1,0) | H12: =IF(AND(Cronograma!$F13<=DATE(2026,11,30),Cronograma!$G13>=DATE(2026,11,1)),1,0) | I12: =IF(AND(Cronograma!$F13<=DATE(2026,12,31),Cronograma!$G13>=DATE(2026,12,1)),1,0) | J12: =IF(AND(Cronograma!$F13<=DATE(2027,1,31),Cronograma!$G13>=DATE(2027,1,1)),1,0) | K12: =IF(AND(Cronograma!$F13<=DATE(2027,2,28),Cronograma!$G13>=DATE(2027,2,1)),1,0) | L12: =IF(AND(Cronograma!$F13<=DATE(2027,3,31),Cronograma!$G13>=DATE(2027,3,1)),1,0) | M12: =IF(AND(Cronograma!$F13<=DATE(2027,4,30),Cronograma!$G13>=DATE(2027,4,1)),1,0) | N12: =IF(AND(Cronograma!$F13<=DATE(2027,5,31),Cronograma!$G13>=DATE(2027,5,1)),1,0) | O12: =IF(AND(Cronograma!$F13<=DATE(2027,6,30),Cronograma!$G13>=DATE(2027,6,1)),1,0) | P12: =IF(AND(Cronograma!$F13<=DATE(2027,7,31),Cronograma!$G13>=DATE(2027,7,1)),1,0) | Q12: =IF(AND(Cronograma!$F13<=DATE(2027,8,31),Cronograma!$G13>=DATE(2027,8,1)),1,0) | R12: =IF(AND(Cronograma!$F13<=DATE(2027,9,30),Cronograma!$G13>=DATE(2027,9,1)),1,0) | S12: =IF(AND(Cronograma!$F13<=DATE(2027,10,31),Cronograma!$G13>=DATE(2027,10,1)),1,0) | T12: =IF(AND(Cronograma!$F13<=DATE(2027,11,30),Cronograma!$G13>=DATE(2027,11,1)),1,0) | U12: =IF(AND(Cronograma!$F13<=DATE(2027,12,31),Cronograma!$G13>=DATE(2027,12,1)),1,0)
A13: =Cronograma!A14 | B13: =Cronograma!B14 | C13: =Cronograma!C14 | D13: =Cronograma!E14 | E13: =IF(AND(Cronograma!$F14<=DATE(2026,8,31),Cronograma!$G14>=DATE(2026,8,1)),1,0) | F13: =IF(AND(Cronograma!$F14<=DATE(2026,9,30),Cronograma!$G14>=DATE(2026,9,1)),1,0) | G13: =IF(AND(Cronograma!$F14<=DATE(2026,10,31),Cronograma!$G14>=DATE(2026,10,1)),1,0) | H13: =IF(AND(Cronograma!$F14<=DATE(2026,11,30),Cronograma!$G14>=DATE(2026,11,1)),1,0) | I13: =IF(AND(Cronograma!$F14<=DATE(2026,12,31),Cronograma!$G14>=DATE(2026,12,1)),1,0) | J13: =IF(AND(Cronograma!$F14<=DATE(2027,1,31),Cronograma!$G14>=DATE(2027,1,1)),1,0) | K13: =IF(AND(Cronograma!$F14<=DATE(2027,2,28),Cronograma!$G14>=DATE(2027,2,1)),1,0) | L13: =IF(AND(Cronograma!$F14<=DATE(2027,3,31),Cronograma!$G14>=DATE(2027,3,1)),1,0) | M13: =IF(AND(Cronograma!$F14<=DATE(2027,4,30),Cronograma!$G14>=DATE(2027,4,1)),1,0) | N13: =IF(AND(Cronograma!$F14<=DATE(2027,5,31),Cronograma!$G14>=DATE(2027,5,1)),1,0) | O13: =IF(AND(Cronograma!$F14<=DATE(2027,6,30),Cronograma!$G14>=DATE(2027,6,1)),1,0) | P13: =IF(AND(Cronograma!$F14<=DATE(2027,7,31),Cronograma!$G14>=DATE(2027,7,1)),1,0) | Q13: =IF(AND(Cronograma!$F14<=DATE(2027,8,31),Cronograma!$G14>=DATE(2027,8,1)),1,0) | R13: =IF(AND(Cronograma!$F14<=DATE(2027,9,30),Cronograma!$G14>=DATE(2027,9,1)),1,0) | S13: =IF(AND(Cronograma!$F14<=DATE(2027,10,31),Cronograma!$G14>=DATE(2027,10,1)),1,0) | T13: =IF(AND(Cronograma!$F14<=DATE(2027,11,30),Cronograma!$G14>=DATE(2027,11,1)),1,0) | U13: =IF(AND(Cronograma!$F14<=DATE(2027,12,31),Cronograma!$G14>=DATE(2027,12,1)),1,0)
A14: =Cronograma!A15 | B14: =Cronograma!B15 | C14: =Cronograma!C15 | D14: =Cronograma!E15 | E14: =IF(AND(Cronograma!$F15<=DATE(2026,8,31),Cronograma!$G15>=DATE(2026,8,1)),1,0) | F14: =IF(AND(Cronograma!$F15<=DATE(2026,9,30),Cronograma!$G15>=DATE(2026,9,1)),1,0) | G14: =IF(AND(Cronograma!$F15<=DATE(2026,10,31),Cronograma!$G15>=DATE(2026,10,1)),1,0) | H14: =IF(AND(Cronograma!$F15<=DATE(2026,11,30),Cronograma!$G15>=DATE(2026,11,1)),1,0) | I14: =IF(AND(Cronograma!$F15<=DATE(2026,12,31),Cronograma!$G15>=DATE(2026,12,1)),1,0) | J14: =IF(AND(Cronograma!$F15<=DATE(2027,1,31),Cronograma!$G15>=DATE(2027,1,1)),1,0) | K14: =IF(AND(Cronograma!$F15<=DATE(2027,2,28),Cronograma!$G15>=DATE(2027,2,1)),1,0) | L14: =IF(AND(Cronograma!$F15<=DATE(2027,3,31),Cronograma!$G15>=DATE(2027,3,1)),1,0) | M14: =IF(AND(Cronograma!$F15<=DATE(2027,4,30),Cronograma!$G15>=DATE(2027,4,1)),1,0) | N14: =IF(AND(Cronograma!$F15<=DATE(2027,5,31),Cronograma!$G15>=DATE(2027,5,1)),1,0) | O14: =IF(AND(Cronograma!$F15<=DATE(2027,6,30),Cronograma!$G15>=DATE(2027,6,1)),1,0) | P14: =IF(AND(Cronograma!$F15<=DATE(2027,7,31),Cronograma!$G15>=DATE(2027,7,1)),1,0) | Q14: =IF(AND(Cronograma!$F15<=DATE(2027,8,31),Cronograma!$G15>=DATE(2027,8,1)),1,0) | R14: =IF(AND(Cronograma!$F15<=DATE(2027,9,30),Cronograma!$G15>=DATE(2027,9,1)),1,0) | S14: =IF(AND(Cronograma!$F15<=DATE(2027,10,31),Cronograma!$G15>=DATE(2027,10,1)),1,0) | T14: =IF(AND(Cronograma!$F15<=DATE(2027,11,30),Cronograma!$G15>=DATE(2027,11,1)),1,0) | U14: =IF(AND(Cronograma!$F15<=DATE(2027,12,31),Cronograma!$G15>=DATE(2027,12,1)),1,0)
A15: =Cronograma!A16 | B15: =Cronograma!B16 | C15: =Cronograma!C16 | D15: =Cronograma!E16 | E15: =IF(AND(Cronograma!$F16<=DATE(2026,8,31),Cronograma!$G16>=DATE(2026,8,1)),1,0) | F15: =IF(AND(Cronograma!$F16<=DATE(2026,9,30),Cronograma!$G16>=DATE(2026,9,1)),1,0) | G15: =IF(AND(Cronograma!$F16<=DATE(2026,10,31),Cronograma!$G16>=DATE(2026,10,1)),1,0) | H15: =IF(AND(Cronograma!$F16<=DATE(2026,11,30),Cronograma!$G16>=DATE(2026,11,1)),1,0) | I15: =IF(AND(Cronograma!$F16<=DATE(2026,12,31),Cronograma!$G16>=DATE(2026,12,1)),1,0) | J15: =IF(AND(Cronograma!$F16<=DATE(2027,1,31),Cronograma!$G16>=DATE(2027,1,1)),1,0) | K15: =IF(AND(Cronograma!$F16<=DATE(2027,2,28),Cronograma!$G16>=DATE(2027,2,1)),1,0) | L15: =IF(AND(Cronograma!$F16<=DATE(2027,3,31),Cronograma!$G16>=DATE(2027,3,1)),1,0) | M15: =IF(AND(Cronograma!$F16<=DATE(2027,4,30),Cronograma!$G16>=DATE(2027,4,1)),1,0) | N15: =IF(AND(Cronograma!$F16<=DATE(2027,5,31),Cronograma!$G16>=DATE(2027,5,1)),1,0) | O15: =IF(AND(Cronograma!$F16<=DATE(2027,6,30),Cronograma!$G16>=DATE(2027,6,1)),1,0) | P15: =IF(AND(Cronograma!$F16<=DATE(2027,7,31),Cronograma!$G16>=DATE(2027,7,1)),1,0) | Q15: =IF(AND(Cronograma!$F16<=DATE(2027,8,31),Cronograma!$G16>=DATE(2027,8,1)),1,0) | R15: =IF(AND(Cronograma!$F16<=DATE(2027,9,30),Cronograma!$G16>=DATE(2027,9,1)),1,0) | S15: =IF(AND(Cronograma!$F16<=DATE(2027,10,31),Cronograma!$G16>=DATE(2027,10,1)),1,0) | T15: =IF(AND(Cronograma!$F16<=DATE(2027,11,30),Cronograma!$G16>=DATE(2027,11,1)),1,0) | U15: =IF(AND(Cronograma!$F16<=DATE(2027,12,31),Cronograma!$G16>=DATE(2027,12,1)),1,0)
... A55: =Cronograma!A56 | B55: =Cronograma!B56 | C55: =Cronograma!C56 | D55: =Cronograma!E56 | E55: =IF(AND(Cronograma!$F56<=DATE(2026,8,31),Cronograma!$G56>=DATE(2026,8,1)),1,0) | F55: =IF(AND(Cronograma!$F56<=DATE(2026,9,30),Cronograma!$G56>=DATE(2026,9,1)),1,0) | G55: =IF(AND(Cronograma!$F56<=DATE(2026,10,31),Cronograma!$G56>=DATE(2026,10,1)),1,0) | H55: =IF(AND(Cronograma!$F56<=DATE(2026,11,30),Cronograma!$G56>=DATE(2026,11,1)),1,0) | I55: =IF(AND(Cronograma!$F56<=DATE(2026,12,31),Cronograma!$G56>=DATE(2026,12,1)),1,0) | J55: =IF(AND(Cronograma!$F56<=DATE(2027,1,31),Cronograma!$G56>=DATE(2027,1,1)),1,0) | K55: =IF(AND(Cronograma!$F56<=DATE(2027,2,28),Cronograma!$G56>=DATE(2027,2,1)),1,0) | L55: =IF(AND(Cronograma!$F56<=DATE(2027,3,31),Cronograma!$G56>=DATE(2027,3,1)),1,0) | M55: =IF(AND(Cronograma!$F56<=DATE(2027,4,30),Cronograma!$G56>=DATE(2027,4,1)),1,0) | N55: =IF(AND(Cronograma!$F56<=DATE(2027,5,31),Cronograma!$G56>=DATE(2027,5,1)),1,0) | O55: =IF(AND(Cronograma!$F56<=DATE(2027,6,30),Cronograma!$G56>=DATE(2027,6,1)),1,0) | P55: =IF(AND(Cronograma!$F56<=DATE(2027,7,31),Cronograma!$G56>=DATE(2027,7,1)),1,0) | Q55: =IF(AND(Cronograma!$F56<=DATE(2027,8,31),Cronograma!$G56>=DATE(2027,8,1)),1,0) | R55: =IF(AND(Cronograma!$F56<=DATE(2027,9,30),Cronograma!$G56>=DATE(2027,9,1)),1,0) | S55: =IF(AND(Cronograma!$F56<=DATE(2027,10,31),Cronograma!$G56>=DATE(2027,10,1)),1,0) | T55: =IF(AND(Cronograma!$F56<=DATE(2027,11,30),Cronograma!$G56>=DATE(2027,11,1)),1,0) | U55: =IF(AND(Cronograma!$F56<=DATE(2027,12,31),Cronograma!$G56>=DATE(2027,12,1)),1,0)
